{
  "$schema": "http://json-schema.org/draft-04/schema#",
  "description": "AccessLocation",
  "allOf": [
    {
      "type": "object",
      "properties": {
        "name": {
          "type": "array",
          "items": {
            "type": "string"
          },
          "x-json-property": "http://bibfra.me/vocab/lite/name"
        },
        "issn": {
          "type": "array",
          "items": {
            "type": "string"
          },
          "x-json-property": "http://bibfra.me/vocab/marc/issn"
        },
        "volume": {
          "type": "array",
          "items": {
            "type": "string"
          },
          "x-json-property": "http://bibfra.me/vocab/marc/volume"
        }
      }
    }
  ]
}
